[
  {
    "title": "Bungalow , Limache Viejo, 3 dormitorios 80 m2",
    "price": 105000000,
    "uf": 2796.6,
    "property_type": "Casa",
    "bedrooms": 3,
    "bathrooms": 1,
    "sqft": 500,
    "address": null,
    "description": "Gran patio, movilización a la puerta, bodega",
    "region": "V",
    "city": "Valparaiso",
    "listing_url": "https://www.yapo.cl/inmuebles/bungalow-limache-viejo-3-dormitorios-80-m2_87394468",
    "transaction": "sale",
    "latitude": null,
    "longitude": null,
    "media": [
      "https://img.yapo.cl/images/21/2125888982.jpg",
      "https://img.yapo.cl/images/21/2133324459.jpg",
      "https://img.yapo.cl/images/21/2134516445.jpg",
      "https://img.yapo.cl/images/21/2123221449.jpg",
      "https://img.yapo.cl/images/21/2192003994.jpg",
      "https://img.yapo.cl/images/21/2167030030.jpg"
    ]
  },
  {
    "title": "Casa para desarmar con amplio terreno urbanizado",
    "price": 85000000,
    "uf": 2263.91,
    "property_type": "Casa",
    "bedrooms": 1,
    "bathrooms": 1,
    "sqft": 474,
    "address": null,
    "description": "Se vende casa de material ligero con Terreno de 474 mts2 plano urbanizado en Belloto sur , cerca de calle Serena y muy cerca a la feria el Belloto y supermercados.\n\nCuenta con luz , agua y alcantarillado. Y con todos los muros medianeros ( panderetas nuevas y muro de ladrillo en la parte posterior .\nTambién tiene un pozo de agua con agua para limpiar y reparar .\n\nReales interesados llamar al teléfono del aviso para más información\n\nLOS HONORARIOS CORRETAJE SE PUEDE PAGAR CON TARJETA DE CRÉDITO.\n\nALTAVISTA PROPIEDADES",
    "region": "V",
    "city": "Valparaiso",
    "listing_url": "https://www.yapo.cl/inmuebles/casa-para-desarmar-con-amplio-terreno-urbanizado_89500518",
    "transaction": "sale",
    "latitude": null,
    "longitude": null,
    "media": [
      "https://img.yapo.cl/images/39/3943384345.jpg",
      "https://img.yapo.cl/images/39/3970742281.jpg",
      "https://img.yapo.cl/images/39/3954887629.jpg",
      "https://img.yapo.cl/images/39/3966882762.jpg",
      "https://img.yapo.cl/images/39/3908411515.jpg",
      "https://img.yapo.cl/images/39/3900096484.jpg",
      "https://img.yapo.cl/images/39/3986521660.jpg",
      "https://img.yapo.cl/images/39/3900796621.jpg",
      "https://img.yapo.cl/images/39/3953724514.jpg",
      "https://img.yapo.cl/images/39/3903776586.jpg",
      "https://img.yapo.cl/images/39/3987325941.jpg",
      "https://img.yapo.cl/images/39/3924295038.jpg",
      "https://img.yapo.cl/images/39/3910124221.jpg",
      "https://img.yapo.cl/images/39/3908440386.jpg",
      "https://img.yapo.cl/images/39/3949373146.jpg",
      "https://img.yapo.cl/images/39/3998829225.jpg"
    ]
  },
  {
    "title": "Se Vende Casa Quilpué Centro",
    "price": 82000000,
    "uf": 2184.01,
    "property_type": "Casa",
    "bedrooms": 2,
    "bathrooms": 1,
    "sqft": 1,
    "address": null,
    "description": "Se Vende Casa Para Remodelar, Calle Araya, Centro de Quilpué, Entre Blanco y Bilbao.  Consta de Living-Comedor, 2 Dormitorios, Baño y Cocina. Ubicación Excelente, Muy Buena Inversión Para Comercio o Vivienda, Necesita Reformas. Consulte y Agende Visitas!!",
    "region": "V",
    "city": "Valparaiso",
    "listing_url": "https://www.yapo.cl/inmuebles/se-vende-casa-quilpue-centro_89385666",
    "transaction": "sale",
    "latitude": -33.04596,
    "longitude": -71.435815,
    "media": [
      "https://img.yapo.cl/images/17/1721890938.jpg",
      "https://img.yapo.cl/images/17/1764507533.jpg",
      "https://img.yapo.cl/images/17/1790077490.jpg",
      "https://img.yapo.cl/images/17/1724170766.jpg"
    ]
  },
  {
    "title": "Vendo Céntrica Casa Colonial",
    "price": 206500855,
    "uf": 5500,
    "property_type": "Casa",
    "bedrooms": 4,
    "bathrooms": 3,
    "sqft": 140,
    "address": null,
    "description": "Vendo céntrica Casa Colonial emplazada en pleno centro de la ciudad de Iquique, calle Tarapaca.\n\n5500 UF\n235 mts2 construidos - 140 mts2 superficie\nContáctanos:\nContactar\nAleymar Propiedades Gestión Inmobiliaria\nHorario de atención: 10:30 a 20:30 hrs.\n\nAtención Inversionista casa antigua ideal para PROYECTOS inmobiliarios, gran oportunidad en pleno centro\nVendo Céntrica Casa Residencial de madera pino oregón, ubicada en Calle Tarapacá, completamente renovado su sistema eléctrico bajo la normativa de seguridad Sec, recién pintada, locomoción colectiva la puerta, de fácil acceso y a pasos de tiendas de retail, farmacias, colegios, jardines infantiles, estaciones de bomberos, Placa Bancaria, Zona Franca, plazas, Restaurantes, Supermercados, Servicios públicos, etc. Ideal para proyectos comerciales, hoteleros, residenciales, Hostel, etc.\n\n1 piso\nLiving Comedor\n3 Dormitorios\n2 Baños\nComedor de Diario\nCocina Amoblada\nLavandería\nTerraza y Patio interior\n\n2 Piso\n1 Dormitorio grande y 1 Baño\n\n3 Piso\nMini Departamento\nQuincho Terraza\nCocina Amoblada\nLiving Comedor\n2 Dormitorios\n1 Baño\nLogia\n\n2% comisión de Corredora",
    "region": "V",
    "city": "Valparaiso",
    "listing_url": "https://www.yapo.cl/inmuebles/vendo-centrica-casa-colonial_85099466",
    "transaction": "sale",
    "latitude": null,
    "longitude": null,
    "media": [
      "https://img.yapo.cl/images/95/9583625247.jpg",
      "https://img.yapo.cl/images/95/9560335118.jpg",
      "https://img.yapo.cl/images/95/9535361154.jpg",
      "https://img.yapo.cl/images/95/9567770595.jpg",
      "https://img.yapo.cl/images/95/9591656717.jpg",
      "https://img.yapo.cl/images/95/9572926244.jpg",
      "https://img.yapo.cl/images/95/9520102495.jpg",
      "https://img.yapo.cl/images/95/9501372022.jpg",
      "https://img.yapo.cl/images/95/9516734825.jpg",
      "https://img.yapo.cl/images/95/9549144266.jpg",
      "https://img.yapo.cl/images/95/9530413793.jpg",
      "https://img.yapo.cl/images/96/9673627301.jpg"
    ]
  },
  {
    "title": "Excelente casa en centro de Quilpué",
    "price": 165000000,
    "uf": 4394.65,
    "property_type": "Casa",
    "bedrooms": 4,
    "bathrooms": 2,
    "sqft": 218,
    "address": null,
    "description": "La casa está ubicada en el sector centro sur de la ciudad de Quilpué, sector residencial consolidado de la ciudad, cuenta con excelente accesibilidad al transporte público, locomoción colectiva a la puerta de la casa, y terminal de buses a Santiago, a media cuadra, y a 15 minutos caminando la estación “El Sol” del metro tren que une a las ciudades de Quilpué con Valparaíso y Limache.\nUbicada a 30 min de Viña del Mar y 40 min de Limache.\nPosee 4 dormitorios, dos baños, living, comedor, cocina amoblada y pequeña bodega. Estacionamiento para 2 vehículos.",
    "region": "V",
    "city": "Valparaiso",
    "listing_url": "https://www.yapo.cl/inmuebles/excelente-casa-en-centro-de-quilpue_89559800",
    "transaction": "sale",
    "latitude": null,
    "longitude": null,
    "media": [
      "https://img.yapo.cl/images/52/5230475897.jpg",
      "https://img.yapo.cl/images/52/5252782328.jpg",
      "https://img.yapo.cl/images/52/5297395190.jpg",
      "https://img.yapo.cl/images/52/5298587176.jpg",
      "https://img.yapo.cl/images/52/5226436961.jpg",
      "https://img.yapo.cl/images/52/5247655550.jpg",
      "https://img.yapo.cl/images/52/5243200038.jpg",
      "https://img.yapo.cl/images/52/5293460398.jpg",
      "https://img.yapo.cl/images/52/5291880707.jpg",
      "https://img.yapo.cl/images/52/5213799433.jpg",
      "https://img.yapo.cl/images/52/5243929046.jpg",
      "https://img.yapo.cl/images/52/5271987119.jpg"
    ]
  },
  {
    "title": "Terreno 240m2 con casa, Forestal Parada 6, Viña",
    "price": 85000000,
    "uf": 2263.91,
    "property_type": "Casa",
    "bedrooms": 2,
    "bathrooms": 2,
    "sqft": 240,
    "address": null,
    "description": "Vendo Terreno plano con casa en Blanca Vergara, Parada 6 de Forestal, Viña del Mar\n\nSuperficie total 240 m2, casa nueva de 2 pisos con Superficie útil 53 m2, (la casa NO se encuentra regularizada).\n\nPrimer Piso material solido: Living y comedor luminosos, cocina amoblada estilo americano, 1 baño de visita, piso cerámico, logia con conexión para lavadora, calefón, lavadero y mueble, amplio patio con terreno plano, 2 entradas para vehículos, reja perimetral metálica, estacionamiento para más de 3 vehículos.\n\nSegundo Piso material liviano, recubierto exterior con fibrocemento Siding: 2 dormitorios, 1 baño completo, pequeña sala estar, piso flotante,\n\nMovilización a la puerta, a una cuadra de Cesfam, Colegio a 2 cuadras, a 5 minutos del plan de Viña, Hospital Gustavo Fricke, estación de metro, comercio en general.\n\nValor de venta: $85.000.000.- (Se aceptan Ofertas razonables)",
    "region": "V",
    "city": "Valparaiso",
    "listing_url": "https://www.yapo.cl/inmuebles/terreno-240m2-con-casa-forestal-parada-6-vina_89087281",
    "transaction": "sale",
    "latitude": null,
    "longitude": null,
    "media": [
      "https://img.yapo.cl/images/61/6108381217.jpg",
      "https://img.yapo.cl/images/61/6133951174.jpg",
      "https://img.yapo.cl/images/61/6142474493.jpg",
      "https://img.yapo.cl/images/61/6185091088.jpg",
      "https://img.yapo.cl/images/61/6127707683.jpg",
      "https://img.yapo.cl/images/61/6144754321.jpg",
      "https://img.yapo.cl/images/61/6161800959.jpg",
      "https://img.yapo.cl/images/61/6104417554.jpg",
      "https://img.yapo.cl/images/61/6112940873.jpg",
      "https://img.yapo.cl/images/61/6188562902.jpg",
      "https://img.yapo.cl/images/61/6197086221.jpg",
      "https://img.yapo.cl/images/61/6122656178.jpg"
    ]
  },
  {
    "title": "Se Vende Casa Quilpué Sector El Retiro",
    "price": 155000000,
    "uf": 4128.31,
    "property_type": "Casa",
    "bedrooms": 4,
    "bathrooms": 2,
    "sqft": 600,
    "address": null,
    "description": "Se vende amplio inmueble, lindo sector residencial, a dos cuadras de Plaza de El Retiro, Quilpué. Consta de living-comedor, 3 dormitorios, 1 baño completo, además de una habitación con baño anexa. Construcción total de 140 m2.  Hermoso terreno plano de 600 m2, con áreas verdes, cercano a locomoción, colegios, zonas deportivas. Estacionamiento para más de 6 vehículos. Muy buen precio por el lindo terreno del inmueble. Vende Exclusivamente Century21 Orión. Consulte y agende visitas.",
    "region": "V",
    "city": "Valparaiso",
    "listing_url": "https://www.yapo.cl/inmuebles/se-vende-casa-quilpue-sector-el-retiro_89570476",
    "transaction": "sale",
    "latitude": -33.039434,
    "longitude": -71.444245,
    "media": [
      "https://img.yapo.cl/images/54/5493847615.jpg",
      "https://img.yapo.cl/images/54/5481360633.jpg",
      "https://img.yapo.cl/images/54/5479676798.jpg",
      "https://img.yapo.cl/images/54/5469469644.jpg",
      "https://img.yapo.cl/images/54/5456982662.jpg",
      "https://img.yapo.cl/images/54/5412682232.jpg",
      "https://img.yapo.cl/images/54/5451335164.jpg"
    ]
  }
]